cvgear/__init__.py
cvgear/framework/__init__.py
cvgear/framework/nested_dict.py
cvgear/framework/darknet/__init__.py
cvgear/framework/darknet/loader.py
cvgear/framework/darknet/parser.py
cvgear/framework/torch/__init__.py
cvgear/framework/torch/loader.py
cvgear/framework/torch/loader_advanced.py
cvgear-0.1.1.dist-info/LICENSE
cvgear-0.1.1.dist-info/METADATA
cvgear-0.1.1.dist-info/WHEEL
cvgear-0.1.1.dist-info/top_level.txt
cvgear-0.1.1.dist-info/RECORD
